fastapi_common-0.3.11.6-py3.10-nspkg.pth
common/fastapi/__init__.py
common/fastapi/aws/__init__.py
common/fastapi/aws/manager.py
common/fastapi/core/__init__.py
common/fastapi/core/app/__init__.py
common/fastapi/core/app/app.py
common/fastapi/core/commands/__init__.py
common/fastapi/core/commands/command.py
common/fastapi/core/commands/load_data.py
common/fastapi/core/commands/make_migrations.py
common/fastapi/core/commands/pytest_cmd.py
common/fastapi/core/commands/runserver.py
common/fastapi/core/parameters/__init__.py
common/fastapi/core/parameters/param_cfg.py
common/fastapi/core/parameters/parameter_manager.py
common/fastapi/core/parameters/managers/__init__.py
common/fastapi/core/parameters/managers/base_manager.py
common/fastapi/core/parameters/managers/command_manager.py
common/fastapi/core/parameters/managers/flag_manager.py
common/fastapi/core/parameters/managers/manager_param.py
common/fastapi/core/parameters/managers/variable_manager.py
common/fastapi/db/__init__.py
common/fastapi/db/connection.py
common/fastapi/db/db_access.py
common/fastapi/db/decorators.py
common/fastapi/db/test_db.py
common/fastapi/db/utils.py
common/fastapi/db/dals/__init__.py
common/fastapi/db/dals/async_crud_dal.py
common/fastapi/db/dals/base_dal.py
common/fastapi/db/dals/crud_dal.py
common/fastapi/db/dals/dal_access.py
common/fastapi/requests/__init__.py
common/fastapi/requests/base_manager.py
common/fastapi/requests/response_type.py
common/fastapi/routing/__init__.py
common/fastapi/routing/base_crud_router.py
common/fastapi/routing/base_router.py
common/fastapi/routing/enum.py
common/fastapi/routing/generic_crud_router.py
common/fastapi/routing/generic_router.py
common/fastapi/routing/utils.py
common/fastapi/schemas/__init__.py
common/fastapi/schemas/base_schema.py
common/fastapi/schemas/http.py
common/fastapi/schemas/request.py
common/fastapi/testing/__init__.py
common/fastapi/testing/decorators.py
common/fastapi/testing/test_case.py
common/fastapi/utils/__init__.py
fastapi_common-0.3.11.6.dist-info/LICENSE
fastapi_common-0.3.11.6.dist-info/METADATA
fastapi_common-0.3.11.6.dist-info/WHEEL
fastapi_common-0.3.11.6.dist-info/namespace_packages.txt
fastapi_common-0.3.11.6.dist-info/top_level.txt
fastapi_common-0.3.11.6.dist-info/RECORD
